agentagenda/__init__.py
agentagenda/main.py
agentagenda/test.py
agentagenda-0.0.12.dist-info/LICENSE
agentagenda-0.0.12.dist-info/METADATA
agentagenda-0.0.12.dist-info/WHEEL
agentagenda-0.0.12.dist-info/top_level.txt
agentagenda-0.0.12.dist-info/RECORD
