Metadata-Version: 2.1
Name: agentagenda
Version: 0.0.12
Summary: A task manager for your agent.
Home-page: https://github.com/AutonomousResearchGroup/agentagenda
Author: Moon
Author-email: shawmakesmagic@gmail.com
License: MIT
Classifier: Development Status :: 2 - Pre-Alpha
Classifier: Intended Audience :: Science/Research
Classifier: License :: OSI Approved :: MIT License
Classifier: Operating System :: POSIX :: Linux
Classifier: Programming Language :: Python :: 3
Classifier: Operating System :: MacOS :: MacOS X
Classifier: Operating System :: Microsoft :: Windows
License-File: LICENSE
Requires-Dist: easycompletion
Requires-Dist: agentmemory
Requires-Dist: agentlogger
